omero_mapr/__init__.py
omero_mapr/apps.py
omero_mapr/custom_context_processor.py
omero_mapr/mapr_settings.py
omero_mapr/show.py
omero_mapr/tree.py
omero_mapr/urls.py
omero_mapr/views.py
omero_mapr/__pycache__/__init__.cpython-39.pyc
omero_mapr/static/mapr/css/ome.mapr.css
omero_mapr/static/mapr/image/compound_icon_16x16.png
omero_mapr/static/mapr/image/favicon.png
omero_mapr/static/mapr/image/gene_icon_16x16.png
omero_mapr/static/mapr/image/organism_icon_16x16.png
omero_mapr/static/mapr/image/phenotype_icon_16x16.png
omero_mapr/static/mapr/image/sirna_icon_16x16.png
omero_mapr/static/mapr/javascript/center_plugin.thumbs.js
omero_mapr/static/mapr/javascript/ome.mapr.js
omero_mapr/static/mapr/javascript/ome.mapr.ui.autocomplete.js
omero_mapr/templates/mapr/base_mapr.html
omero_mapr/templates/mapr/metadata_general.html
omero_mapr/templates/webclient/data/includes/right_plugin.general.js.html
omero_mapr/templatetags/__init__.py
omero_mapr/templatetags/mapr_filters.py
omero_mapr/templatetags/mapr_tags.py
omero_mapr/testlib/__init__.py
omero_mapr/utils/__init__.py
omero_mapr/utils/version.py
omero_mapr/utils/__pycache__/__init__.cpython-39.pyc
omero_mapr/utils/__pycache__/version.cpython-39.pyc
omero_mapr-0.5.3.dist-info/LICENSE
omero_mapr-0.5.3.dist-info/METADATA
omero_mapr-0.5.3.dist-info/WHEEL
omero_mapr-0.5.3.dist-info/top_level.txt
omero_mapr-0.5.3.dist-info/RECORD
