Metadata-Version: 2.1
Name: omero-mapr
Version: 0.5.3
Summary: MAPR is a Python plugin for OMERO.web
Home-page: https://github.com/ome/omero-mapr
Download-URL: https://github.com/ome/omero-mapr/tarball/0.5.3
Author: The Open Microscopy Team
Author-email: ome-devel@lists.openmicroscopy.org.uk
License: AGPLv3
Classifier: Development Status :: 5 - Production/Stable
Classifier: Environment :: Web Environment
Classifier: Framework :: Django
Classifier: Intended Audience :: End Users/Desktop
Classifier: Intended Audience :: Science/Research
Classifier: License :: OSI Approved :: GNU Affero General Public License v3 or later (AGPLv3+)
Classifier: Natural Language :: English
Classifier: Operating System :: OS Independent
Classifier: Programming Language :: JavaScript
Classifier: Programming Language :: Python :: 3
Classifier: Topic :: Internet :: WWW/HTTP
Classifier: Topic :: Internet :: WWW/HTTP :: Dynamic Content
Classifier: Topic :: Internet :: WWW/HTTP :: WSGI
Classifier: Topic :: Scientific/Engineering :: Visualization
Classifier: Topic :: Software Development :: Libraries :: Application Frameworks
Classifier: Topic :: Text Processing :: Markup :: HTML
Requires-Python: >=3
License-File: LICENSE
Requires-Dist: requests
Requires-Dist: omero-web[redis]>=5.14.0
